{
	"name": "Notebook 3",
	"properties": {
		"nbformat": 4,
		"nbformat_minor": 2,
		"bigDataPool": {
			"referenceName": "mysparkpool",
			"type": "BigDataPoolReference"
		},
		"sessionProperties": {
			"driverMemory": "56g",
			"driverCores": 8,
			"executorMemory": "56g",
			"executorCores": 8,
			"numExecutors": 2,
			"runAsWorkspaceSystemIdentity": false,
			"conf": {
				"spark.dynamicAllocation.enabled": "false",
				"spark.dynamicAllocation.minExecutors": "2",
				"spark.dynamicAllocation.maxExecutors": "2",
				"spark.autotune.trackingId": "23dfae25-8c7d-458f-bc41-aa5237c12549"
			}
		},
		"metadata": {
			"saveOutput": true,
			"synapse_widget": {
				"version": "0.1"
			},
			"enableDebugMode": false,
			"language_info": {
				"name": "python"
			},
			"a365ComputeOptions": {
				"id": "/subscriptions/0c6ee07f-0d38-4a6b-b8f8-93814aae9823/resourceGroups/rg-synapse/providers/Microsoft.Synapse/workspaces/swift-demo/bigDataPools/mysparkpool",
				"name": "mysparkpool",
				"type": "Spark",
				"endpoint": "https://swift-demo.dev.azuresynapse.net/livyApi/versions/2019-11-01-preview/sparkPools/mysparkpool",
				"auth": {
					"type": "AAD",
					"authResource": "https://dev.azuresynapse.net",
					"authHeader": null
				},
				"sparkVersion": "3.4",
				"nodeCount": 10,
				"cores": 8,
				"memory": 56,
				"extraHeader": null
			},
			"sessionKeepAliveTimeout": 30
		},
		"cells": [
			{
				"cell_type": "code",
				"source": [
					"print (\"hello\")"
				]
			}
		]
	}
}